mehc_curation/cleaning/__init__.py
mehc_curation/cleaning/__main__.py
mehc_curation/cleaning/config/__init__.py
mehc_curation/cleaning/config/cleaning_config.py
mehc_curation/cleaning/core/__init__.py
mehc_curation/cleaning/core/engine.py
mehc_curation/cleaning/core/output_manager.py
mehc_curation/cleaning/core/pipeline.py
mehc_curation/cleaning/core/template_manager.py
mehc_curation/cleaning/utils/__init__.py
mehc_curation/cleaning/utils/cleaning_utils.py
mehc_curation/dat/metals.txt
mehc_curation/normalization/__init__.py
mehc_curation/normalization/__main__.py
mehc_curation/normalization/config/__init__.py
mehc_curation/normalization/config/normalization_config.py
mehc_curation/normalization/core/__init__.py
mehc_curation/normalization/core/engine.py
mehc_curation/normalization/core/output_manager.py
mehc_curation/normalization/core/pipeline.py
mehc_curation/normalization/core/template_manager.py
mehc_curation/normalization/utils/__init__.py
mehc_curation/normalization/utils/normalization_utils.py
mehc_curation/refinement/__init__.py
mehc_curation/refinement/__main__.py
mehc_curation/refinement/config/__init__.py
mehc_curation/refinement/config/refinement_config.py
mehc_curation/refinement/core/__init__.py
mehc_curation/refinement/core/output_manager.py
mehc_curation/refinement/core/pipeline.py
mehc_curation/refinement/core/template_manager.py
mehc_curation/refinement/utils/__init__.py
mehc_curation/template_report/cleaning_title.txt
mehc_curation/template_report/deduplicate.txt
mehc_curation/template_report/destereoisomerization.txt
mehc_curation/template_report/detautomerization.txt
mehc_curation/template_report/end.txt
mehc_curation/template_report/inorganic_removal.txt
mehc_curation/template_report/mixture_removal.txt
mehc_curation/template_report/neutralization.txt
mehc_curation/template_report/normalization_title.txt
mehc_curation/template_report/organometallic_removal.txt
mehc_curation/template_report/refining.txt
mehc_curation-1.0.5.dist-info/licenses/LICENSE
mehc_curation-1.0.5.dist-info/METADATA
mehc_curation-1.0.5.dist-info/WHEEL
mehc_curation-1.0.5.dist-info/entry_points.txt
mehc_curation-1.0.5.dist-info/top_level.txt
mehc_curation-1.0.5.dist-info/RECORD
