Metadata-Version: 2.4
Name: mehc-curation
Version: 1.0.5
Summary: A comprehensive toolkit for molecular data curation, validation, cleaning, and normalization
Home-page: https://github.com/biochem-data-sci/mehc-curation
Author: Thanh-Hoang Nguyen-Vo
Author-email: Thanh-Hoang Nguyen-Vo <nvthoang@gmail.com>
License: MIT
Project-URL: Homepage, https://github.com/biochem-data-sci/mehc-curation
Project-URL: Documentation, https://github.com/biochem-data-sci/mehc-curation#readme
Project-URL: Repository, https://github.com/biochem-data-sci/mehc-curation
Project-URL: Bug Tracker, https://github.com/biochem-data-sci/mehc-curation/issues
Keywords: chemistry,SMILES,molecular data,validation,cleaning,normalization,cheminformatics,RDKit
Classifier: Development Status :: 4 - Beta
Classifier: Intended Audience :: Science/Research
Classifier: Topic :: Scientific/Engineering :: Chemistry
Classifier: License :: OSI Approved :: MIT License
Classifier: Programming Language :: Python :: 3
Classifier: Programming Language :: Python :: 3.7
Classifier: Programming Language :: Python :: 3.8
Classifier: Programming Language :: Python :: 3.9
Classifier: Programming Language :: Python :: 3.10
Classifier: Programming Language :: Python :: 3.11
Requires-Python: >=3.7
License-File: LICENSE
Requires-Dist: pandas>=1.3.0
Requires-Dist: parallel-pandas>=0.2.8
Provides-Extra: dev
Requires-Dist: pytest>=7.0.0; extra == "dev"
Requires-Dist: pytest-cov>=4.0.0; extra == "dev"
Requires-Dist: black>=22.0.0; extra == "dev"
Requires-Dist: flake8>=5.0.0; extra == "dev"
Dynamic: author
Dynamic: home-page
Dynamic: license-file
Dynamic: requires-python
